{
  "logoType": "default",
  "logo": {
    "lucideIcon": "",
    "imagePath": "",
    "imageLink": ""
  },
  "logoScale": 1.2,
  "iconColorType": "default",
  "wordmark": "Obsidian",
  "customFont": "interfaceFont",
  "fontSize": "4em",
  "fontColorType": "default",
  "fontWeight": 600,
  "maxResults": 5,
  "showStarredFiles": false,
  "showRecentFiles": false,
  "maxRecentFiles": 5,
  "storeRecentFile": true,
  "showPath": true,
  "selectionHighlight": "default",
  "showShortcuts": true,
  "markdownOnly": false,
  "unresolvedLinks": false,
  "recentFilesStore": [
    {
      "filepath": "How to add files, commit, and push to Github using console.md",
      "timestamp": 1716982785709
    },
    {
      "filepath": "_Note.md",
      "timestamp": 1716982747237
    },
    {
      "filepath": "templates/toefl/Writing 1 Integrated.md",
      "timestamp": 1716981404445
    },
    {
      "filepath": "Writing 2 (1).md",
      "timestamp": 1716981400557
    },
    {
      "filepath": "templates/toefl/Speaking 3 Integrated Read Listen.md",
      "timestamp": 1716977381333
    }
  ],
  "starredFileStore": [],
  "searchDelay": 0,
  "replaceNewTabs": true,
  "newTabOnStart": false,
  "closePreviousSessionTabs": false,
  "omnisearch": false
}